pandasai_lancedb/__init__.py
pandasai_lancedb/lancedb.py
pandasai_lancedb-0.1.4.dist-info/LICENSE
pandasai_lancedb-0.1.4.dist-info/METADATA
pandasai_lancedb-0.1.4.dist-info/WHEEL
pandasai_lancedb-0.1.4.dist-info/RECORD
