Metadata-Version: 2.3
Name: pandasai-lancedb
Version: 0.1.4
Summary: LanceDB integration for PandaAI
License: Proprietary
Author: Gabriele Venturi
Requires-Python: >=3.8,<3.12
Classifier: License :: Other/Proprietary License
Classifier: Programming Language :: Python :: 3
Classifier: Programming Language :: Python :: 3.8
Classifier: Programming Language :: Python :: 3.9
Classifier: Programming Language :: Python :: 3.10
Classifier: Programming Language :: Python :: 3.11
Requires-Dist: lancedb (>=0.5.0,<0.6.0)
Requires-Dist: numpy (==1.23.2)
Requires-Dist: pandasai (>=3.0.0b4)
Requires-Dist: sentence-transformers (>=2.2.2,<3.0.0)
Project-URL: Documentation, https://docs.getpanda.ai/
Project-URL: Repository, https://github.com/sinaptik-ai/pandas-ai
